<?xml version="1.0" encoding="utf-8"?>
<TextureAtlas imagePath="Blitzo Intro.png">
	<!-- Created with Adobe Animate version 19.2.1.408 -->
	<!-- http://www.adobe.com/products/animate.html -->
	<SubTexture name="Idle0000" x="0" y="0" width="935" height="980"/>
	<SubTexture name="Idle0001" x="935" y="0" width="935" height="980"/>
	<SubTexture name="Idle0002" x="935" y="0" width="935" height="980"/>
	<SubTexture name="Idle0003" x="1870" y="0" width="935" height="980"/>
	<SubTexture name="Idle0004" x="1870" y="0" width="935" height="980"/>
	<SubTexture name="Idle0005" x="2805" y="0" width="935" height="980"/>
	<SubTexture name="Idle0006" x="2805" y="0" width="935" height="980"/>
	<SubTexture name="Idle0007" x="935" y="2940" width="935" height="980"/>
	<SubTexture name="Idle0008" x="935" y="2940" width="935" height="980"/>
	<SubTexture name="Idle0009" x="935" y="2940" width="935" height="980"/>
	<SubTexture name="Idle0010" x="935" y="2940" width="935" height="980"/>
	<SubTexture name="Idle0011" x="935" y="2940" width="935" height="980"/>
	<SubTexture name="Idle0012" x="935" y="2940" width="935" height="980"/>
	<SubTexture name="Merequetengue0000" x="0" y="2940" width="935" height="980"/>
	<SubTexture name="Merequetengue0001" x="0" y="2940" width="935" height="980"/>
	<SubTexture name="Merequetengue0002" x="0" y="2940" width="935" height="980"/>
	<SubTexture name="Merequetengue0003" x="0" y="2940" width="935" height="980"/>
	<SubTexture name="Merequetengue0004" x="0" y="2940" width="935" height="980"/>
	<SubTexture name="Merequetengue0005" x="0" y="2940" width="935" height="980"/>
	<SubTexture name="Merequetengue0006" x="0" y="2940" width="935" height="980"/>
	<SubTexture name="Merequetengue0007" x="0" y="2940" width="935" height="980"/>
	<SubTexture name="Merequetengue0008" x="0" y="2940" width="935" height="980"/>
	<SubTexture name="Merequetengue0009" x="0" y="2940" width="935" height="980"/>
	<SubTexture name="Merequetengue0010" x="0" y="2940" width="935" height="980"/>
	<SubTexture name="Merequetengue0011" x="0" y="2940" width="935" height="980"/>
	<SubTexture name="Merequetengue0012" x="0" y="2940" width="935" height="980"/>
	<SubTexture name="Merequetengue0013" x="0" y="2940" width="935" height="980"/>
	<SubTexture name="Merequetengue0014" x="0" y="2940" width="935" height="980"/>
	<SubTexture name="Merequetengue0015" x="0" y="2940" width="935" height="980"/>
	<SubTexture name="Merequetengue0016" x="0" y="2940" width="935" height="980"/>
	<SubTexture name="Merequetengue0017" x="0" y="2940" width="935" height="980"/>
	<SubTexture name="Merequetengue0018" x="0" y="2940" width="935" height="980"/>
	<SubTexture name="Merequetengue0019" x="0" y="2940" width="935" height="980"/>
	<SubTexture name="Merequetengue0020" x="0" y="2940" width="935" height="980"/>
	<SubTexture name="Merequetengue0021" x="0" y="2940" width="935" height="980"/>
	<SubTexture name="Merequetengue0022" x="0" y="2940" width="935" height="980"/>
	<SubTexture name="Merequetengue0023" x="0" y="2940" width="935" height="980"/>
	<SubTexture name="Merequetengue0024" x="0" y="2940" width="935" height="980"/>
	<SubTexture name="Merequetengue0025" x="0" y="2940" width="935" height="980"/>
	<SubTexture name="Merequetengue0026" x="0" y="2940" width="935" height="980"/>
	<SubTexture name="Merequetengue0027" x="0" y="2940" width="935" height="980"/>
	<SubTexture name="Merequetengue0028" x="0" y="2940" width="935" height="980"/>
	<SubTexture name="Merequetengue0029" x="0" y="2940" width="935" height="980"/>
	<SubTexture name="Merequetengue0030" x="0" y="2940" width="935" height="980"/>
	<SubTexture name="Merequetengue0031" x="0" y="2940" width="935" height="980"/>
	<SubTexture name="Merequetengue0032" x="0" y="2940" width="935" height="980"/>
	<SubTexture name="Merequetengue0033" x="0" y="2940" width="935" height="980"/>
	<SubTexture name="Merequetengue0034" x="0" y="2940" width="935" height="980"/>
	<SubTexture name="Merequetengue0035" x="0" y="2940" width="935" height="980"/>
	<SubTexture name="Merequetengue0036" x="0" y="2940" width="935" height="980"/>
	<SubTexture name="Merequetengue0037" x="0" y="2940" width="935" height="980"/>
	<SubTexture name="Merequetengue0038" x="0" y="2940" width="935" height="980"/>
	<SubTexture name="Merequetengue0039" x="0" y="2940" width="935" height="980"/>
	<SubTexture name="Merequetengue0040" x="0" y="2940" width="935" height="980"/>
	<SubTexture name="Merequetengue0041" x="0" y="2940" width="935" height="980"/>
	<SubTexture name="Merequetengue0042" x="0" y="2940" width="935" height="980"/>
	<SubTexture name="Merequetengue0043" x="0" y="2940" width="935" height="980"/>
	<SubTexture name="Merequetengue0044" x="0" y="2940" width="935" height="980"/>
	<SubTexture name="Merequetengue0045" x="0" y="2940" width="935" height="980"/>
	<SubTexture name="Merequetengue0046" x="0" y="2940" width="935" height="980"/>
	<SubTexture name="Merequetengue0047" x="0" y="2940" width="935" height="980"/>
	<SubTexture name="Merequetengue0048" x="0" y="2940" width="935" height="980"/>
	<SubTexture name="Merequetengue0049" x="0" y="2940" width="935" height="980"/>
	<SubTexture name="Merequetengue0050" x="0" y="2940" width="935" height="980"/>
	<SubTexture name="Merequetengue0051" x="0" y="2940" width="935" height="980"/>
	<SubTexture name="Merequetengue0052" x="0" y="2940" width="935" height="980"/>
	<SubTexture name="Merequetengue0053" x="0" y="2940" width="935" height="980"/>
	<SubTexture name="Merequetengue0054" x="0" y="2940" width="935" height="980"/>
	<SubTexture name="Merequetengue0055" x="0" y="2940" width="935" height="980"/>
	<SubTexture name="Merequetengue0056" x="0" y="2940" width="935" height="980"/>
	<SubTexture name="Merequetengue0057" x="0" y="2940" width="935" height="980"/>
	<SubTexture name="Merequetengue0058" x="0" y="2940" width="935" height="980"/>
	<SubTexture name="Merequetengue0059" x="0" y="2940" width="935" height="980"/>
	<SubTexture name="Merequetengue0060" x="0" y="2940" width="935" height="980"/>
	<SubTexture name="Merequetengue0061" x="0" y="2940" width="935" height="980"/>
	<SubTexture name="Merequetengue0062" x="0" y="2940" width="935" height="980"/>
	<SubTexture name="Merequetengue0063" x="0" y="2940" width="935" height="980"/>
	<SubTexture name="Merequetengue0064" x="0" y="2940" width="935" height="980"/>
	<SubTexture name="Merequetengue0065" x="0" y="2940" width="935" height="980"/>
	<SubTexture name="Merequetengue0066" x="0" y="2940" width="935" height="980"/>
	<SubTexture name="Merequetengue0067" x="0" y="2940" width="935" height="980"/>
	<SubTexture name="Merequetengue0068" x="0" y="2940" width="935" height="980"/>
	<SubTexture name="Merequetengue0069" x="0" y="2940" width="935" height="980"/>
	<SubTexture name="Merequetengue0070" x="0" y="2940" width="935" height="980"/>
	<SubTexture name="Merequetengue0071" x="0" y="2940" width="935" height="980"/>
	<SubTexture name="Merequetengue0072" x="0" y="2940" width="935" height="980"/>
	<SubTexture name="Merequetengue0073" x="0" y="2940" width="935" height="980"/>
	<SubTexture name="Merequetengue0074" x="0" y="2940" width="935" height="980"/>
	<SubTexture name="Merequetengue0075" x="0" y="2940" width="935" height="980"/>
	<SubTexture name="Merequetengue0076" x="0" y="2940" width="935" height="980"/>
	<SubTexture name="Merequetengue0077" x="0" y="2940" width="935" height="980"/>
	<SubTexture name="Merequetengue0078" x="0" y="2940" width="935" height="980"/>
	<SubTexture name="Merequetengue0079" x="0" y="2940" width="935" height="980"/>
	<SubTexture name="Merequetengue0080" x="0" y="2940" width="935" height="980"/>
	<SubTexture name="Merequetengue0081" x="0" y="2940" width="935" height="980"/>
	<SubTexture name="Merequetengue0082" x="0" y="2940" width="935" height="980"/>
	<SubTexture name="Merequetengue0083" x="0" y="2940" width="935" height="980"/>
	<SubTexture name="Merequetengue0084" x="0" y="2940" width="935" height="980"/>
	<SubTexture name="Merequetengue0085" x="0" y="2940" width="935" height="980"/>
	<SubTexture name="Merequetengue0086" x="0" y="2940" width="935" height="980"/>
	<SubTexture name="Merequetengue0087" x="0" y="2940" width="935" height="980"/>
	<SubTexture name="Merequetengue0088" x="0" y="2940" width="935" height="980"/>
	<SubTexture name="Merequetengue0089" x="0" y="2940" width="935" height="980"/>
	<SubTexture name="Merequetengue0090" x="0" y="2940" width="935" height="980"/>
	<SubTexture name="Merequetengue0091" x="0" y="2940" width="935" height="980"/>
	<SubTexture name="Merequetengue0092" x="0" y="2940" width="935" height="980"/>
	<SubTexture name="Merequetengue0093" x="0" y="2940" width="935" height="980"/>
	<SubTexture name="Merequetengue0094" x="0" y="2940" width="935" height="980"/>
	<SubTexture name="Merequetengue0095" x="0" y="2940" width="935" height="980"/>
	<SubTexture name="Merequetengue0096" x="0" y="2940" width="935" height="980"/>
	<SubTexture name="Merequetengue0097" x="0" y="2940" width="935" height="980"/>
	<SubTexture name="Merequetengue0098" x="0" y="2940" width="935" height="980"/>
	<SubTexture name="Merequetengue0099" x="0" y="2940" width="935" height="980"/>
	<SubTexture name="Merequetengue0100" x="0" y="2940" width="935" height="980"/>
	<SubTexture name="Merequetengue0101" x="0" y="2940" width="935" height="980"/>
	<SubTexture name="Merequetengue0102" x="0" y="2940" width="935" height="980"/>
	<SubTexture name="Merequetengue0103" x="0" y="2940" width="935" height="980"/>
	<SubTexture name="Merequetengue0104" x="0" y="2940" width="935" height="980"/>
	<SubTexture name="Merequetengue0105" x="0" y="2940" width="935" height="980"/>
	<SubTexture name="Merequetengue0106" x="0" y="2940" width="935" height="980"/>
	<SubTexture name="Merequetengue0107" x="0" y="2940" width="935" height="980"/>
	<SubTexture name="Merequetengue0108" x="0" y="2940" width="935" height="980"/>
	<SubTexture name="Merequetengue0109" x="0" y="2940" width="935" height="980"/>
	<SubTexture name="Merequetengue0110" x="0" y="2940" width="935" height="980"/>
	<SubTexture name="Merequetengue0111" x="0" y="2940" width="935" height="980"/>
	<SubTexture name="Merequetengue0112" x="0" y="2940" width="935" height="980"/>
	<SubTexture name="Merequetengue0113" x="0" y="2940" width="935" height="980"/>
	<SubTexture name="Merequetengue0114" x="0" y="2940" width="935" height="980"/>
	<SubTexture name="Merequetengue0115" x="0" y="2940" width="935" height="980"/>
	<SubTexture name="Merequetengue0116" x="0" y="2940" width="935" height="980"/>
	<SubTexture name="Merequetengue0117" x="0" y="2940" width="935" height="980"/>
	<SubTexture name="Merequetengue0118" x="0" y="2940" width="935" height="980"/>
	<SubTexture name="Merequetengue0119" x="0" y="2940" width="935" height="980"/>
	<SubTexture name="Merequetengue0120" x="0" y="2940" width="935" height="980"/>
	<SubTexture name="Merequetengue0121" x="0" y="2940" width="935" height="980"/>
	<SubTexture name="Merequetengue0122" x="0" y="2940" width="935" height="980"/>
	<SubTexture name="Merequetengue0123" x="0" y="2940" width="935" height="980"/>
	<SubTexture name="Merequetengue0124" x="0" y="2940" width="935" height="980"/>
	<SubTexture name="Merequetengue0125" x="0" y="2940" width="935" height="980"/>
	<SubTexture name="Merequetengue0126" x="0" y="2940" width="935" height="980"/>
	<SubTexture name="Merequetengue0127" x="0" y="2940" width="935" height="980"/>
	<SubTexture name="Merequetengue0128" x="0" y="2940" width="935" height="980"/>
	<SubTexture name="Merequetengue0129" x="0" y="2940" width="935" height="980"/>
	<SubTexture name="Merequetengue0130" x="0" y="2940" width="935" height="980"/>
	<SubTexture name="Merequetengue0131" x="0" y="2940" width="935" height="980"/>
	<SubTexture name="Merequetengue0132" x="0" y="2940" width="935" height="980"/>
	<SubTexture name="Merequetengue0133" x="0" y="2940" width="935" height="980"/>
	<SubTexture name="Merequetengue0134" x="0" y="2940" width="935" height="980"/>
	<SubTexture name="Merequetengue0135" x="0" y="2940" width="935" height="980"/>
	<SubTexture name="Merequetengue0136" x="0" y="2940" width="935" height="980"/>
	<SubTexture name="Merequetengue0137" x="0" y="2940" width="935" height="980"/>
	<SubTexture name="Merequetengue0138" x="0" y="2940" width="935" height="980"/>
	<SubTexture name="Merequetengue0139" x="0" y="2940" width="935" height="980"/>
	<SubTexture name="Merequetengue0140" x="0" y="2940" width="935" height="980"/>
	<SubTexture name="Merequetengue0141" x="0" y="2940" width="935" height="980"/>
	<SubTexture name="Merequetengue0142" x="0" y="2940" width="935" height="980"/>
	<SubTexture name="Merequetengue0143" x="0" y="2940" width="935" height="980"/>
	<SubTexture name="Merequetengue0144" x="0" y="2940" width="935" height="980"/>
	<SubTexture name="Merequetengue0145" x="0" y="2940" width="935" height="980"/>
	<SubTexture name="Merequetengue0146" x="0" y="2940" width="935" height="980"/>
	<SubTexture name="Merequetengue0147" x="0" y="2940" width="935" height="980"/>
	<SubTexture name="Merequetengue0148" x="0" y="2940" width="935" height="980"/>
	<SubTexture name="Merequetengue0149" x="0" y="2940" width="935" height="980"/>
	<SubTexture name="Merequetengue0150" x="0" y="2940" width="935" height="980"/>
	<SubTexture name="Merequetengue0151" x="0" y="2940" width="935" height="980"/>
	<SubTexture name="Merequetengue0152" x="0" y="2940" width="935" height="980"/>
	<SubTexture name="Merequetengue0153" x="0" y="2940" width="935" height="980"/>
	<SubTexture name="Merequetengue0154" x="0" y="2940" width="935" height="980"/>
	<SubTexture name="Merequetengue0155" x="0" y="2940" width="935" height="980"/>
	<SubTexture name="Merequetengue0156" x="0" y="2940" width="935" height="980"/>
	<SubTexture name="Merequetengue0157" x="0" y="2940" width="935" height="980"/>
	<SubTexture name="Merequetengue0158" x="0" y="2940" width="935" height="980"/>
	<SubTexture name="Merequetengue0159" x="0" y="2940" width="935" height="980"/>
	<SubTexture name="Merequetengue0160" x="0" y="2940" width="935" height="980"/>
	<SubTexture name="Merequetengue0161" x="0" y="2940" width="935" height="980"/>
	<SubTexture name="Merequetengue0162" x="0" y="2940" width="935" height="980"/>
	<SubTexture name="Merequetengue0163" x="0" y="2940" width="935" height="980"/>
	<SubTexture name="Merequetengue0164" x="0" y="2940" width="935" height="980"/>
	<SubTexture name="Merequetengue0165" x="0" y="2940" width="935" height="980"/>
	<SubTexture name="Merequetengue0166" x="0" y="2940" width="935" height="980"/>
	<SubTexture name="Merequetengue0167" x="0" y="2940" width="935" height="980"/>
	<SubTexture name="Merequetengue0168" x="0" y="2940" width="935" height="980"/>
	<SubTexture name="Merequetengue0169" x="0" y="2940" width="935" height="980"/>
	<SubTexture name="Merequetengue0170" x="0" y="2940" width="935" height="980"/>
	<SubTexture name="Merequetengue0171" x="0" y="2940" width="935" height="980"/>
	<SubTexture name="Merequetengue0172" x="0" y="2940" width="935" height="980"/>
	<SubTexture name="Merequetengue0173" x="0" y="2940" width="935" height="980"/>
	<SubTexture name="Merequetengue0174" x="0" y="2940" width="935" height="980"/>
	<SubTexture name="Merequetengue0175" x="0" y="2940" width="935" height="980"/>
	<SubTexture name="Merequetengue0176" x="0" y="2940" width="935" height="980"/>
	<SubTexture name="Merequetengue0177" x="0" y="2940" width="935" height="980"/>
	<SubTexture name="Merequetengue0178" x="0" y="2940" width="935" height="980"/>
	<SubTexture name="Merequetengue0179" x="0" y="2940" width="935" height="980"/>
	<SubTexture name="Merequetengue0180" x="0" y="2940" width="935" height="980"/>
	<SubTexture name="Merequetengue0181" x="0" y="2940" width="935" height="980"/>
	<SubTexture name="Merequetengue0182" x="0" y="2940" width="935" height="980"/>
	<SubTexture name="Merequetengue0183" x="0" y="2940" width="935" height="980"/>
	<SubTexture name="Merequetengue0184" x="0" y="2940" width="935" height="980"/>
	<SubTexture name="Merequetengue0185" x="0" y="2940" width="935" height="980"/>
	<SubTexture name="Merequetengue0186" x="0" y="2940" width="935" height="980"/>
	<SubTexture name="Merequetengue0187" x="0" y="2940" width="935" height="980"/>
	<SubTexture name="Merequetengue0188" x="0" y="2940" width="935" height="980"/>
	<SubTexture name="Merequetengue0189" x="0" y="2940" width="935" height="980"/>
	<SubTexture name="Merequetengue0190" x="0" y="2940" width="935" height="980"/>
	<SubTexture name="Merequetengue0191" x="0" y="2940" width="935" height="980"/>
	<SubTexture name="Merequetengue0192" x="0" y="2940" width="935" height="980"/>
	<SubTexture name="Merequetengue0193" x="0" y="2940" width="935" height="980"/>
	<SubTexture name="Merequetengue0194" x="0" y="2940" width="935" height="980"/>
	<SubTexture name="Merequetengue0195" x="0" y="2940" width="935" height="980"/>
	<SubTexture name="Merequetengue0196" x="0" y="2940" width="935" height="980"/>
	<SubTexture name="Merequetengue0197" x="0" y="2940" width="935" height="980"/>
	<SubTexture name="Merequetengue0198" x="0" y="2940" width="935" height="980"/>
	<SubTexture name="Merequetengue0199" x="0" y="2940" width="935" height="980"/>
	<SubTexture name="Merequetengue0200" x="0" y="2940" width="935" height="980"/>
	<SubTexture name="Merequetengue0201" x="0" y="2940" width="935" height="980"/>
	<SubTexture name="Merequetengue0202" x="0" y="2940" width="935" height="980"/>
	<SubTexture name="Merequetengue0203" x="0" y="2940" width="935" height="980"/>
	<SubTexture name="Merequetengue0204" x="0" y="2940" width="935" height="980"/>
	<SubTexture name="Merequetengue0205" x="0" y="2940" width="935" height="980"/>
	<SubTexture name="Merequetengue0206" x="0" y="2940" width="935" height="980"/>
	<SubTexture name="Merequetengue0207" x="0" y="2940" width="935" height="980"/>
	<SubTexture name="Merequetengue0208" x="0" y="2940" width="935" height="980"/>
	<SubTexture name="Merequetengue0209" x="0" y="2940" width="935" height="980"/>
	<SubTexture name="Merequetengue0210" x="0" y="2940" width="935" height="980"/>
	<SubTexture name="Merequetengue0211" x="0" y="2940" width="935" height="980"/>
	<SubTexture name="Merequetengue0212" x="0" y="2940" width="935" height="980"/>
	<SubTexture name="Merequetengue0213" x="0" y="2940" width="935" height="980"/>
	<SubTexture name="Merequetengue0214" x="0" y="2940" width="935" height="980"/>
	<SubTexture name="Merequetengue0215" x="0" y="2940" width="935" height="980"/>
	<SubTexture name="Merequetengue0216" x="0" y="2940" width="935" height="980"/>
	<SubTexture name="Merequetengue0217" x="0" y="2940" width="935" height="980"/>
	<SubTexture name="Microphone0000" x="935" y="2940" width="935" height="980"/>
	<SubTexture name="Microphone0001" x="935" y="2940" width="935" height="980"/>
	<SubTexture name="Microphone0002" x="935" y="2940" width="935" height="980"/>
	<SubTexture name="Microphone0003" x="0" y="980" width="935" height="980"/>
	<SubTexture name="Microphone0004" x="935" y="980" width="935" height="980"/>
	<SubTexture name="Microphone0005" x="1870" y="980" width="935" height="980"/>
	<SubTexture name="Microphone0006" x="2805" y="980" width="935" height="980"/>
	<SubTexture name="Microphone0007" x="0" y="1960" width="935" height="980"/>
	<SubTexture name="Microphone0008" x="935" y="1960" width="935" height="980"/>
	<SubTexture name="Microphone0009" x="1870" y="1960" width="935" height="980"/>
	<SubTexture name="Microphone0010" x="2805" y="1960" width="935" height="980"/>
	<SubTexture name="Microphone0011" x="0" y="2940" width="935" height="980"/>
	<SubTexture name="Microphone0012" x="0" y="2940" width="935" height="980"/>
	<SubTexture name="Microphone0013" x="0" y="2940" width="935" height="980"/>
	<SubTexture name="Microphone0014" x="0" y="2940" width="935" height="980"/>
	<SubTexture name="Microphone0015" x="0" y="2940" width="935" height="980"/>
	<SubTexture name="Microphone0016" x="0" y="2940" width="935" height="980"/>
	<SubTexture name="Microphone0017" x="0" y="2940" width="935" height="980"/>
	<SubTexture name="Microphone0018" x="0" y="2940" width="935" height="980"/>
	<SubTexture name="Microphone0019" x="0" y="2940" width="935" height="980"/>
	<SubTexture name="Microphone0020" x="0" y="2940" width="935" height="980"/>
	<SubTexture name="Microphone0021" x="0" y="2940" width="935" height="980"/>
	<SubTexture name="Microphone0022" x="0" y="2940" width="935" height="980"/>
	<SubTexture name="Mondongo0000" x="935" y="2940" width="935" height="980"/>
	<SubTexture name="Mondongo0001" x="935" y="2940" width="935" height="980"/>
	<SubTexture name="Mondongo0002" x="935" y="2940" width="935" height="980"/>
	<SubTexture name="Mondongo0003" x="935" y="2940" width="935" height="980"/>
	<SubTexture name="Mondongo0004" x="935" y="2940" width="935" height="980"/>
	<SubTexture name="Mondongo0005" x="935" y="2940" width="935" height="980"/>
	<SubTexture name="Mondongo0006" x="935" y="2940" width="935" height="980"/>
	<SubTexture name="Mondongo0007" x="935" y="2940" width="935" height="980"/>
	<SubTexture name="Mondongo0008" x="935" y="2940" width="935" height="980"/>
	<SubTexture name="Mondongo0009" x="935" y="2940" width="935" height="980"/>
	<SubTexture name="Mondongo0010" x="935" y="2940" width="935" height="980"/>
	<SubTexture name="Mondongo0011" x="935" y="2940" width="935" height="980"/>
	<SubTexture name="Mondongo0012" x="935" y="2940" width="935" height="980"/>
	<SubTexture name="Mondongo0013" x="935" y="2940" width="935" height="980"/>
	<SubTexture name="Mondongo0014" x="935" y="2940" width="935" height="980"/>
	<SubTexture name="Mondongo0015" x="935" y="2940" width="935" height="980"/>
	<SubTexture name="Mondongo0016" x="935" y="2940" width="935" height="980"/>
	<SubTexture name="Mondongo0017" x="935" y="2940" width="935" height="980"/>
	<SubTexture name="Mondongo0018" x="935" y="2940" width="935" height="980"/>
	<SubTexture name="Mondongo0019" x="935" y="2940" width="935" height="980"/>
	<SubTexture name="Mondongo0020" x="935" y="2940" width="935" height="980"/>
	<SubTexture name="Mondongo0021" x="935" y="2940" width="935" height="980"/>
	<SubTexture name="Mondongo0022" x="935" y="2940" width="935" height="980"/>
	<SubTexture name="Mondongo0023" x="935" y="2940" width="935" height="980"/>
	<SubTexture name="Mondongo0024" x="935" y="2940" width="935" height="980"/>
	<SubTexture name="Mondongo0025" x="935" y="2940" width="935" height="980"/>
	<SubTexture name="Mondongo0026" x="935" y="2940" width="935" height="980"/>
	<SubTexture name="Mondongo0027" x="935" y="2940" width="935" height="980"/>
	<SubTexture name="Mondongo0028" x="935" y="2940" width="935" height="980"/>
	<SubTexture name="Mondongo0029" x="935" y="2940" width="935" height="980"/>
	<SubTexture name="Mondongo0030" x="935" y="2940" width="935" height="980"/>
	<SubTexture name="Mondongo0031" x="935" y="2940" width="935" height="980"/>
	<SubTexture name="Mondongo0032" x="935" y="2940" width="935" height="980"/>
	<SubTexture name="Mondongo0033" x="935" y="2940" width="935" height="980"/>
	<SubTexture name="Mondongo0034" x="935" y="2940" width="935" height="980"/>
	<SubTexture name="Mondongo0035" x="935" y="2940" width="935" height="980"/>
	<SubTexture name="Mondongo0036" x="935" y="2940" width="935" height="980"/>
	<SubTexture name="Mondongo0037" x="935" y="2940" width="935" height="980"/>
	<SubTexture name="Mondongo0038" x="935" y="2940" width="935" height="980"/>
	<SubTexture name="Mondongo0039" x="935" y="2940" width="935" height="980"/>
	<SubTexture name="Mondongo0040" x="935" y="2940" width="935" height="980"/>
	<SubTexture name="Mondongo0041" x="935" y="2940" width="935" height="980"/>
	<SubTexture name="Mondongo0042" x="935" y="2940" width="935" height="980"/>
	<SubTexture name="Mondongo0043" x="935" y="2940" width="935" height="980"/>
	<SubTexture name="Mondongo0044" x="935" y="2940" width="935" height="980"/>
	<SubTexture name="Mondongo0045" x="935" y="2940" width="935" height="980"/>
	<SubTexture name="Mondongo0046" x="935" y="2940" width="935" height="980"/>
	<SubTexture name="Mondongo0047" x="935" y="2940" width="935" height="980"/>
	<SubTexture name="Mondongo0048" x="935" y="2940" width="935" height="980"/>
	<SubTexture name="Mondongo0049" x="935" y="2940" width="935" height="980"/>
	<SubTexture name="Mondongo0050" x="935" y="2940" width="935" height="980"/>
	<SubTexture name="Mondongo0051" x="935" y="2940" width="935" height="980"/>
	<SubTexture name="Mondongo0052" x="935" y="2940" width="935" height="980"/>
	<SubTexture name="Mondongo0053" x="935" y="2940" width="935" height="980"/>
	<SubTexture name="Mondongo0054" x="935" y="2940" width="935" height="980"/>
	<SubTexture name="Mondongo0055" x="935" y="2940" width="935" height="980"/>
	<SubTexture name="Mondongo0056" x="935" y="2940" width="935" height="980"/>
	<SubTexture name="Mondongo0057" x="935" y="2940" width="935" height="980"/>
	<SubTexture name="Mondongo0058" x="935" y="2940" width="935" height="980"/>
	<SubTexture name="Mondongo0059" x="935" y="2940" width="935" height="980"/>
	<SubTexture name="Mondongo0060" x="935" y="2940" width="935" height="980"/>
	<SubTexture name="Mondongo0061" x="935" y="2940" width="935" height="980"/>
	<SubTexture name="Mondongo0062" x="935" y="2940" width="935" height="980"/>
	<SubTexture name="Mondongo0063" x="935" y="2940" width="935" height="980"/>
	<SubTexture name="Mondongo0064" x="935" y="2940" width="935" height="980"/>
	<SubTexture name="Mondongo0065" x="935" y="2940" width="935" height="980"/>
	<SubTexture name="Mondongo0066" x="935" y="2940" width="935" height="980"/>
	<SubTexture name="Mondongo0067" x="935" y="2940" width="935" height="980"/>
	<SubTexture name="Mondongo0068" x="935" y="2940" width="935" height="980"/>
	<SubTexture name="Mondongo0069" x="935" y="2940" width="935" height="980"/>
	<SubTexture name="Mondongo0070" x="935" y="2940" width="935" height="980"/>
	<SubTexture name="Mondongo0071" x="935" y="2940" width="935" height="980"/>
	<SubTexture name="Mondongo0072" x="935" y="2940" width="935" height="980"/>
	<SubTexture name="Mondongo0073" x="935" y="2940" width="935" height="980"/>
	<SubTexture name="Mondongo0074" x="935" y="2940" width="935" height="980"/>
	<SubTexture name="Mondongo0075" x="935" y="2940" width="935" height="980"/>
	<SubTexture name="Mondongo0076" x="935" y="2940" width="935" height="980"/>
	<SubTexture name="Mondongo0077" x="935" y="2940" width="935" height="980"/>
	<SubTexture name="Mondongo0078" x="935" y="2940" width="935" height="980"/>
	<SubTexture name="Mondongo0079" x="935" y="2940" width="935" height="980"/>
	<SubTexture name="Mondongo0080" x="935" y="2940" width="935" height="980"/>
	<SubTexture name="Mondongo0081" x="935" y="2940" width="935" height="980"/>
	<SubTexture name="Mondongo0082" x="935" y="2940" width="935" height="980"/>
	<SubTexture name="Mondongo0083" x="935" y="2940" width="935" height="980"/>
	<SubTexture name="Mondongo0084" x="935" y="2940" width="935" height="980"/>
	<SubTexture name="Mondongo0085" x="935" y="2940" width="935" height="980"/>
	<SubTexture name="Mondongo0086" x="935" y="2940" width="935" height="980"/>
	<SubTexture name="Mondongo0087" x="935" y="2940" width="935" height="980"/>
	<SubTexture name="Mondongo0088" x="935" y="2940" width="935" height="980"/>
	<SubTexture name="Mondongo0089" x="935" y="2940" width="935" height="980"/>
	<SubTexture name="Mondongo0090" x="935" y="2940" width="935" height="980"/>
	<SubTexture name="Mondongo0091" x="935" y="2940" width="935" height="980"/>
	<SubTexture name="Mondongo0092" x="935" y="2940" width="935" height="980"/>
	<SubTexture name="Mondongo0093" x="935" y="2940" width="935" height="980"/>
	<SubTexture name="Mondongo0094" x="935" y="2940" width="935" height="980"/>
	<SubTexture name="Mondongo0095" x="935" y="2940" width="935" height="980"/>
	<SubTexture name="Mondongo0096" x="935" y="2940" width="935" height="980"/>
	<SubTexture name="Mondongo0097" x="935" y="2940" width="935" height="980"/>
	<SubTexture name="Mondongo0098" x="935" y="2940" width="935" height="980"/>
	<SubTexture name="Mondongo0099" x="935" y="2940" width="935" height="980"/>
	<SubTexture name="Mondongo0100" x="935" y="2940" width="935" height="980"/>
	<SubTexture name="Mondongo0101" x="935" y="2940" width="935" height="980"/>
	<SubTexture name="Mondongo0102" x="935" y="2940" width="935" height="980"/>
	<SubTexture name="Mondongo0103" x="935" y="2940" width="935" height="980"/>
	<SubTexture name="Mondongo0104" x="935" y="2940" width="935" height="980"/>
	<SubTexture name="Mondongo0105" x="935" y="2940" width="935" height="980"/>
	<SubTexture name="Mondongo0106" x="935" y="2940" width="935" height="980"/>
	<SubTexture name="Mondongo0107" x="935" y="2940" width="935" height="980"/>
	<SubTexture name="Mondongo0108" x="935" y="2940" width="935" height="980"/>
	<SubTexture name="Mondongo0109" x="935" y="2940" width="935" height="980"/>
	<SubTexture name="Mondongo0110" x="935" y="2940" width="935" height="980"/>
	<SubTexture name="Mondongo0111" x="935" y="2940" width="935" height="980"/>
	<SubTexture name="Mondongo0112" x="935" y="2940" width="935" height="980"/>
	<SubTexture name="Mondongo0113" x="935" y="2940" width="935" height="980"/>
	<SubTexture name="Mondongo0114" x="935" y="2940" width="935" height="980"/>
	<SubTexture name="Mondongo0115" x="935" y="2940" width="935" height="980"/>
	<SubTexture name="Mondongo0116" x="935" y="2940" width="935" height="980"/>
	<SubTexture name="Mondongo0117" x="935" y="2940" width="935" height="980"/>
	<SubTexture name="Mondongo0118" x="935" y="2940" width="935" height="980"/>
	<SubTexture name="Mondongo0119" x="935" y="2940" width="935" height="980"/>
	<SubTexture name="Mondongo0120" x="935" y="2940" width="935" height="980"/>
	<SubTexture name="Mondongo0121" x="935" y="2940" width="935" height="980"/>
	<SubTexture name="Mondongo0122" x="935" y="2940" width="935" height="980"/>
	<SubTexture name="Mondongo0123" x="935" y="2940" width="935" height="980"/>
	<SubTexture name="Mondongo0124" x="935" y="2940" width="935" height="980"/>
	<SubTexture name="Mondongo0125" x="935" y="2940" width="935" height="980"/>
	<SubTexture name="Mondongo0126" x="935" y="2940" width="935" height="980"/>
	<SubTexture name="Mondongo0127" x="935" y="2940" width="935" height="980"/>
	<SubTexture name="Mondongo0128" x="935" y="2940" width="935" height="980"/>
	<SubTexture name="Mondongo0129" x="935" y="2940" width="935" height="980"/>
	<SubTexture name="Mondongo0130" x="935" y="2940" width="935" height="980"/>
	<SubTexture name="Mondongo0131" x="935" y="2940" width="935" height="980"/>
	<SubTexture name="Mondongo0132" x="935" y="2940" width="935" height="980"/>
	<SubTexture name="Mondongo0133" x="935" y="2940" width="935" height="980"/>
	<SubTexture name="Mondongo0134" x="935" y="2940" width="935" height="980"/>
	<SubTexture name="Mondongo0135" x="935" y="2940" width="935" height="980"/>
	<SubTexture name="Mondongo0136" x="935" y="2940" width="935" height="980"/>
	<SubTexture name="Mondongo0137" x="935" y="2940" width="935" height="980"/>
	<SubTexture name="Mondongo0138" x="935" y="2940" width="935" height="980"/>
	<SubTexture name="Mondongo0139" x="935" y="2940" width="935" height="980"/>
	<SubTexture name="Mondongo0140" x="935" y="2940" width="935" height="980"/>
	<SubTexture name="Mondongo0141" x="935" y="2940" width="935" height="980"/>
	<SubTexture name="Mondongo0142" x="935" y="2940" width="935" height="980"/>
	<SubTexture name="Mondongo0143" x="935" y="2940" width="935" height="980"/>
	<SubTexture name="Mondongo0144" x="935" y="2940" width="935" height="980"/>
	<SubTexture name="Mondongo0145" x="935" y="2940" width="935" height="980"/>
	<SubTexture name="Mondongo0146" x="935" y="2940" width="935" height="980"/>
	<SubTexture name="Mondongo0147" x="935" y="2940" width="935" height="980"/>
	<SubTexture name="Mondongo0148" x="935" y="2940" width="935" height="980"/>
	<SubTexture name="Mondongo0149" x="935" y="2940" width="935" height="980"/>
	<SubTexture name="Mondongo0150" x="935" y="2940" width="935" height="980"/>
	<SubTexture name="Mondongo0151" x="935" y="2940" width="935" height="980"/>
	<SubTexture name="Mondongo0152" x="935" y="2940" width="935" height="980"/>
	<SubTexture name="Mondongo0153" x="935" y="2940" width="935" height="980"/>
	<SubTexture name="Mondongo0154" x="935" y="2940" width="935" height="980"/>
	<SubTexture name="Mondongo0155" x="935" y="2940" width="935" height="980"/>
	<SubTexture name="Mondongo0156" x="935" y="2940" width="935" height="980"/>
	<SubTexture name="Mondongo0157" x="935" y="2940" width="935" height="980"/>
	<SubTexture name="Mondongo0158" x="935" y="2940" width="935" height="980"/>
	<SubTexture name="Mondongo0159" x="935" y="2940" width="935" height="980"/>
	<SubTexture name="Mondongo0160" x="935" y="2940" width="935" height="980"/>
	<SubTexture name="Mondongo0161" x="935" y="2940" width="935" height="980"/>
	<SubTexture name="Mondongo0162" x="935" y="2940" width="935" height="980"/>
	<SubTexture name="Mondongo0163" x="935" y="2940" width="935" height="980"/>
	<SubTexture name="Mondongo0164" x="935" y="2940" width="935" height="980"/>
	<SubTexture name="Mondongo0165" x="935" y="2940" width="935" height="980"/>
	<SubTexture name="Mondongo0166" x="935" y="2940" width="935" height="980"/>
	<SubTexture name="Mondongo0167" x="935" y="2940" width="935" height="980"/>
	<SubTexture name="Mondongo0168" x="935" y="2940" width="935" height="980"/>
	<SubTexture name="Mondongo0169" x="935" y="2940" width="935" height="980"/>
	<SubTexture name="Mondongo0170" x="935" y="2940" width="935" height="980"/>
	<SubTexture name="Mondongo0171" x="935" y="2940" width="935" height="980"/>
	<SubTexture name="Mondongo0172" x="935" y="2940" width="935" height="980"/>
	<SubTexture name="Mondongo0173" x="935" y="2940" width="935" height="980"/>
	<SubTexture name="Mondongo0174" x="935" y="2940" width="935" height="980"/>
	<SubTexture name="Mondongo0175" x="935" y="2940" width="935" height="980"/>
	<SubTexture name="Mondongo0176" x="935" y="2940" width="935" height="980"/>
	<SubTexture name="Mondongo0177" x="935" y="2940" width="935" height="980"/>
	<SubTexture name="Mondongo0178" x="935" y="2940" width="935" height="980"/>
	<SubTexture name="Mondongo0179" x="935" y="2940" width="935" height="980"/>
	<SubTexture name="Mondongo0180" x="935" y="2940" width="935" height="980"/>
	<SubTexture name="Mondongo0181" x="935" y="2940" width="935" height="980"/>
	<SubTexture name="Mondongo0182" x="935" y="2940" width="935" height="980"/>
	<SubTexture name="Mondongo0183" x="935" y="2940" width="935" height="980"/>
	<SubTexture name="Mondongo0184" x="935" y="2940" width="935" height="980"/>
	<SubTexture name="Mondongo0185" x="935" y="2940" width="935" height="980"/>
	<SubTexture name="Mondongo0186" x="935" y="2940" width="935" height="980"/>
	<SubTexture name="Mondongo0187" x="935" y="2940" width="935" height="980"/>
	<SubTexture name="Mondongo0188" x="935" y="2940" width="935" height="980"/>
	<SubTexture name="Mondongo0189" x="935" y="2940" width="935" height="980"/>
	<SubTexture name="Mondongo0190" x="935" y="2940" width="935" height="980"/>
	<SubTexture name="Mondongo0191" x="935" y="2940" width="935" height="980"/>
	<SubTexture name="Mondongo0192" x="935" y="2940" width="935" height="980"/>
	<SubTexture name="Mondongo0193" x="935" y="2940" width="935" height="980"/>
	<SubTexture name="Mondongo0194" x="935" y="2940" width="935" height="980"/>
	<SubTexture name="Mondongo0195" x="935" y="2940" width="935" height="980"/>
	<SubTexture name="Mondongo0196" x="935" y="2940" width="935" height="980"/>
	<SubTexture name="Mondongo0197" x="935" y="2940" width="935" height="980"/>
	<SubTexture name="Mondongo0198" x="935" y="2940" width="935" height="980"/>
	<SubTexture name="Mondongo0199" x="935" y="2940" width="935" height="980"/>
	<SubTexture name="Mondongo0200" x="935" y="2940" width="935" height="980"/>
	<SubTexture name="Mondongo0201" x="935" y="2940" width="935" height="980"/>
	<SubTexture name="Mondongo0202" x="935" y="2940" width="935" height="980"/>
	<SubTexture name="Mondongo0203" x="935" y="2940" width="935" height="980"/>
	<SubTexture name="Mondongo0204" x="935" y="2940" width="935" height="980"/>
	<SubTexture name="Mondongo0205" x="935" y="2940" width="935" height="980"/>
	<SubTexture name="Mondongo0206" x="935" y="2940" width="935" height="980"/>
	<SubTexture name="Mondongo0207" x="935" y="2940" width="935" height="980"/>
	<SubTexture name="Mondongo0208" x="935" y="2940" width="935" height="980"/>
	<SubTexture name="Mondongo0209" x="935" y="2940" width="935" height="980"/>
	<SubTexture name="Mondongo0210" x="935" y="2940" width="935" height="980"/>
	<SubTexture name="Mondongo0211" x="935" y="2940" width="935" height="980"/>
	<SubTexture name="Mondongo0212" x="935" y="2940" width="935" height="980"/>
	<SubTexture name="Mondongo0213" x="935" y="2940" width="935" height="980"/>
	<SubTexture name="Mondongo0214" x="935" y="2940" width="935" height="980"/>
	<SubTexture name="Mondongo0215" x="935" y="2940" width="935" height="980"/>
	<SubTexture name="Mondongo0216" x="935" y="2940" width="935" height="980"/>
	<SubTexture name="Mondongo0217" x="935" y="2940" width="935" height="980"/>
	<SubTexture name="Mondongo0218" x="935" y="2940" width="935" height="980"/>
	<SubTexture name="Mondongo0219" x="935" y="2940" width="935" height="980"/>
	<SubTexture name="Mondongo0220" x="935" y="2940" width="935" height="980"/>
	<SubTexture name="Mondongo0221" x="935" y="2940" width="935" height="980"/>
	<SubTexture name="Mondongo0222" x="935" y="2940" width="935" height="980"/>
	<SubTexture name="Mondongo0223" x="935" y="2940" width="935" height="980"/>
	<SubTexture name="Mondongo0224" x="935" y="2940" width="935" height="980"/>
	<SubTexture name="Mondongo0225" x="935" y="2940" width="935" height="980"/>
	<SubTexture name="Mondongo0226" x="935" y="2940" width="935" height="980"/>
	<SubTexture name="Mondongo0227" x="935" y="2940" width="935" height="980"/>
	<SubTexture name="Mondongo0228" x="935" y="2940" width="935" height="980"/>
	<SubTexture name="Mondongo0229" x="935" y="2940" width="935" height="980"/>
	<SubTexture name="Mondongo0230" x="935" y="2940" width="935" height="980"/>
	<SubTexture name="Mondongo0231" x="935" y="2940" width="935" height="980"/>
	<SubTexture name="Mondongo0232" x="935" y="2940" width="935" height="980"/>
	<SubTexture name="Mondongo0233" x="935" y="2940" width="935" height="980"/>
	<SubTexture name="Mondongo0234" x="935" y="2940" width="935" height="980"/>
	<SubTexture name="Mondongo0235" x="935" y="2940" width="935" height="980"/>
	<SubTexture name="Mondongo0236" x="935" y="2940" width="935" height="980"/>
	<SubTexture name="Mondongo0237" x="935" y="2940" width="935" height="980"/>
	<SubTexture name="Mondongo0238" x="935" y="2940" width="935" height="980"/>
	<SubTexture name="Mondongo0239" x="935" y="2940" width="935" height="980"/>
	<SubTexture name="Mondongo0240" x="935" y="2940" width="935" height="980"/>
	<SubTexture name="Mondongo0241" x="935" y="2940" width="935" height="980"/>
	<SubTexture name="Mondongo0242" x="935" y="2940" width="935" height="980"/>
	<SubTexture name="Mondongo0243" x="935" y="2940" width="935" height="980"/>
	<SubTexture name="Mondongo0244" x="935" y="2940" width="935" height="980"/>
	<SubTexture name="Mondongo0245" x="935" y="2940" width="935" height="980"/>
	<SubTexture name="Mondongo0246" x="935" y="2940" width="935" height="980"/>
	<SubTexture name="Mondongo0247" x="935" y="2940" width="935" height="980"/>
	<SubTexture name="Mondongo0248" x="935" y="2940" width="935" height="980"/>
	<SubTexture name="Mondongo0249" x="935" y="2940" width="935" height="980"/>
	<SubTexture name="Mondongo0250" x="935" y="2940" width="935" height="980"/>
	<SubTexture name="Mondongo0251" x="935" y="2940" width="935" height="980"/>
	<SubTexture name="Mondongo0252" x="935" y="2940" width="935" height="980"/>
	<SubTexture name="Mondongo0253" x="935" y="2940" width="935" height="980"/>
	<SubTexture name="Mondongo0254" x="935" y="2940" width="935" height="980"/>
	<SubTexture name="Mondongo0255" x="935" y="2940" width="935" height="980"/>
	<SubTexture name="Mondongo0256" x="935" y="2940" width="935" height="980"/>
	<SubTexture name="Mondongo0257" x="935" y="2940" width="935" height="980"/>
	<SubTexture name="Mondongo0258" x="935" y="2940" width="935" height="980"/>
	<SubTexture name="Mondongo0259" x="935" y="2940" width="935" height="980"/>
	<SubTexture name="Mondongo0260" x="935" y="2940" width="935" height="980"/>
	<SubTexture name="Mondongo0261" x="935" y="2940" width="935" height="980"/>
	<SubTexture name="Mondongo0262" x="935" y="2940" width="935" height="980"/>
	<SubTexture name="Mondongo0263" x="935" y="2940" width="935" height="980"/>
	<SubTexture name="Mondongo0264" x="935" y="2940" width="935" height="980"/>
	<SubTexture name="Mondongo0265" x="935" y="2940" width="935" height="980"/>
	<SubTexture name="Mondongo0266" x="935" y="2940" width="935" height="980"/>
	<SubTexture name="Mondongo0267" x="935" y="2940" width="935" height="980"/>
	<SubTexture name="Mondongo0268" x="935" y="2940" width="935" height="980"/>
	<SubTexture name="Mondongo0269" x="935" y="2940" width="935" height="980"/>
	<SubTexture name="Mondongo0270" x="935" y="2940" width="935" height="980"/>
	<SubTexture name="Mondongo0271" x="935" y="2940" width="935" height="980"/>
	<SubTexture name="Mondongo0272" x="935" y="2940" width="935" height="980"/>
	<SubTexture name="Mondongo0273" x="935" y="2940" width="935" height="980"/>
	<SubTexture name="Mondongo0274" x="935" y="2940" width="935" height="980"/>
	<SubTexture name="Mondongo0275" x="935" y="2940" width="935" height="980"/>
	<SubTexture name="Mondongo0276" x="935" y="2940" width="935" height="980"/>
	<SubTexture name="Mondongo0277" x="935" y="2940" width="935" height="980"/>
	<SubTexture name="Mondongo0278" x="935" y="2940" width="935" height="980"/>
	<SubTexture name="Mondongo0279" x="935" y="2940" width="935" height="980"/>
	<SubTexture name="Mondongo0280" x="935" y="2940" width="935" height="980"/>
	<SubTexture name="Mondongo0281" x="935" y="2940" width="935" height="980"/>
	<SubTexture name="Mondongo0282" x="935" y="2940" width="935" height="980"/>
	<SubTexture name="Mondongo0283" x="935" y="2940" width="935" height="980"/>
	<SubTexture name="Mondongo0284" x="935" y="2940" width="935" height="980"/>
	<SubTexture name="Mondongo0285" x="935" y="2940" width="935" height="980"/>
	<SubTexture name="Mondongo0286" x="935" y="2940" width="935" height="980"/>
	<SubTexture name="Mondongo0287" x="935" y="2940" width="935" height="980"/>
	<SubTexture name="Mondongo0288" x="935" y="2940" width="935" height="980"/>
	<SubTexture name="Mondongo0289" x="935" y="2940" width="935" height="980"/>
	<SubTexture name="Mondongo0290" x="935" y="2940" width="935" height="980"/>
	<SubTexture name="Mondongo0291" x="935" y="2940" width="935" height="980"/>
	<SubTexture name="Mondongo0292" x="935" y="2940" width="935" height="980"/>
	<SubTexture name="Mondongo0293" x="935" y="2940" width="935" height="980"/>
	<SubTexture name="Mondongo0294" x="935" y="2940" width="935" height="980"/>
	<SubTexture name="Mondongo0295" x="935" y="2940" width="935" height="980"/>
	<SubTexture name="Mondongo0296" x="935" y="2940" width="935" height="980"/>
	<SubTexture name="Mondongo0297" x="935" y="2940" width="935" height="980"/>
	<SubTexture name="Mondongo0298" x="935" y="2940" width="935" height="980"/>
	<SubTexture name="Mondongo0299" x="935" y="2940" width="935" height="980"/>
	<SubTexture name="Mondongo0300" x="935" y="2940" width="935" height="980"/>
	<SubTexture name="Mondongo0301" x="935" y="2940" width="935" height="980"/>
	<SubTexture name="Mondongo0302" x="935" y="2940" width="935" height="980"/>
	<SubTexture name="Mondongo0303" x="935" y="2940" width="935" height="980"/>
	<SubTexture name="Mondongo0304" x="935" y="2940" width="935" height="980"/>
	<SubTexture name="Mondongo0305" x="935" y="2940" width="935" height="980"/>
	<SubTexture name="Mondongo0306" x="935" y="2940" width="935" height="980"/>
	<SubTexture name="Mondongo0307" x="935" y="2940" width="935" height="980"/>
	<SubTexture name="Mondongo0308" x="935" y="2940" width="935" height="980"/>
	<SubTexture name="Mondongo0309" x="935" y="2940" width="935" height="980"/>
	<SubTexture name="Mondongo0310" x="935" y="2940" width="935" height="980"/>
	<SubTexture name="Mondongo0311" x="935" y="2940" width="935" height="980"/>
	<SubTexture name="Mondongo0312" x="935" y="2940" width="935" height="980"/>
	<SubTexture name="Mondongo0313" x="935" y="2940" width="935" height="980"/>
	<SubTexture name="Mondongo0314" x="935" y="2940" width="935" height="980"/>
	<SubTexture name="Mondongo0315" x="935" y="2940" width="935" height="980"/>
	<SubTexture name="Mondongo0316" x="935" y="2940" width="935" height="980"/>
	<SubTexture name="Mondongo0317" x="935" y="2940" width="935" height="980"/>
	<SubTexture name="Mondongo0318" x="935" y="2940" width="935" height="980"/>
	<SubTexture name="Mondongo0319" x="935" y="2940" width="935" height="980"/>
	<SubTexture name="Mondongo0320" x="935" y="2940" width="935" height="980"/>
	<SubTexture name="Mondongo0321" x="935" y="2940" width="935" height="980"/>
	<SubTexture name="Mondongo0322" x="935" y="2940" width="935" height="980"/>
	<SubTexture name="Mondongo0323" x="935" y="2940" width="935" height="980"/>
	<SubTexture name="Mondongo0324" x="935" y="2940" width="935" height="980"/>
	<SubTexture name="Mondongo0325" x="935" y="2940" width="935" height="980"/>
	<SubTexture name="Mondongo0326" x="935" y="2940" width="935" height="980"/>
	<SubTexture name="Mondongo0327" x="935" y="2940" width="935" height="980"/>
	<SubTexture name="Mondongo0328" x="935" y="2940" width="935" height="980"/>
	<SubTexture name="Mondongo0329" x="935" y="2940" width="935" height="980"/>
	<SubTexture name="Mondongo0330" x="935" y="2940" width="935" height="980"/>
	<SubTexture name="Mondongo0331" x="935" y="2940" width="935" height="980"/>
	<SubTexture name="Mondongo0332" x="935" y="2940" width="935" height="980"/>
	<SubTexture name="Mondongo0333" x="935" y="2940" width="935" height="980"/>
	<SubTexture name="Mondongo0334" x="935" y="2940" width="935" height="980"/>
	<SubTexture name="Mondongo0335" x="935" y="2940" width="935" height="980"/>
	<SubTexture name="Mondongo0336" x="935" y="2940" width="935" height="980"/>
	<SubTexture name="Mondongo0337" x="935" y="2940" width="935" height="980"/>
	<SubTexture name="Mondongo0338" x="935" y="2940" width="935" height="980"/>
	<SubTexture name="Mondongo0339" x="935" y="2940" width="935" height="980"/>
	<SubTexture name="Mondongo0340" x="935" y="2940" width="935" height="980"/>
	<SubTexture name="Mondongo0341" x="935" y="2940" width="935" height="980"/>
	<SubTexture name="Mondongo0342" x="935" y="2940" width="935" height="980"/>
	<SubTexture name="Mondongo0343" x="935" y="2940" width="935" height="980"/>
	<SubTexture name="Mondongo0344" x="935" y="2940" width="935" height="980"/>
	<SubTexture name="Mondongo0345" x="935" y="2940" width="935" height="980"/>
	<SubTexture name="Mondongo0346" x="935" y="2940" width="935" height="980"/>
	<SubTexture name="Mondongo0347" x="935" y="2940" width="935" height="980"/>
	<SubTexture name="Mondongo0348" x="935" y="2940" width="935" height="980"/>
	<SubTexture name="Mondongo0349" x="935" y="2940" width="935" height="980"/>
	<SubTexture name="Mondongo0350" x="935" y="2940" width="935" height="980"/>
	<SubTexture name="Mondongo0351" x="935" y="2940" width="935" height="980"/>
	<SubTexture name="Mondongo0352" x="935" y="2940" width="935" height="980"/>
	<SubTexture name="Mondongo0353" x="935" y="2940" width="935" height="980"/>
	<SubTexture name="Mondongo0354" x="935" y="2940" width="935" height="980"/>
	<SubTexture name="Mondongo0355" x="935" y="2940" width="935" height="980"/>
	<SubTexture name="Mondongo0356" x="935" y="2940" width="935" height="980"/>
	<SubTexture name="Mondongo0357" x="935" y="2940" width="935" height="980"/>
	<SubTexture name="Mondongo0358" x="935" y="2940" width="935" height="980"/>
	<SubTexture name="Mondongo0359" x="935" y="2940" width="935" height="980"/>
	<SubTexture name="Mondongo0360" x="935" y="2940" width="935" height="980"/>
	<SubTexture name="Mondongo0361" x="935" y="2940" width="935" height="980"/>
	<SubTexture name="Mondongo0362" x="935" y="2940" width="935" height="980"/>
	<SubTexture name="Mondongo0363" x="935" y="2940" width="935" height="980"/>
	<SubTexture name="Mondongo0364" x="935" y="2940" width="935" height="980"/>
	<SubTexture name="Mondongo0365" x="935" y="2940" width="935" height="980"/>
	<SubTexture name="Mondongo0366" x="935" y="2940" width="935" height="980"/>
	<SubTexture name="Mondongo0367" x="935" y="2940" width="935" height="980"/>
	<SubTexture name="Mondongo0368" x="935" y="2940" width="935" height="980"/>
	<SubTexture name="Mondongo0369" x="935" y="2940" width="935" height="980"/>
	<SubTexture name="Mondongo0370" x="935" y="2940" width="935" height="980"/>
	<SubTexture name="Mondongo0371" x="935" y="2940" width="935" height="980"/>
	<SubTexture name="Mondongo0372" x="935" y="2940" width="935" height="980"/>
	<SubTexture name="Mondongo0373" x="935" y="2940" width="935" height="980"/>
	<SubTexture name="Mondongo0374" x="935" y="2940" width="935" height="980"/>
	<SubTexture name="Mondongo0375" x="935" y="2940" width="935" height="980"/>
	<SubTexture name="Mondongo0376" x="935" y="2940" width="935" height="980"/>
	<SubTexture name="Mondongo0377" x="935" y="2940" width="935" height="980"/>
	<SubTexture name="Mondongo0378" x="935" y="2940" width="935" height="980"/>
	<SubTexture name="Mondongo0379" x="935" y="2940" width="935" height="980"/>
	<SubTexture name="Mondongo0380" x="935" y="2940" width="935" height="980"/>
	<SubTexture name="Mondongo0381" x="935" y="2940" width="935" height="980"/>
	<SubTexture name="Mondongo0382" x="935" y="2940" width="935" height="980"/>
	<SubTexture name="Mondongo0383" x="935" y="2940" width="935" height="980"/>
	<SubTexture name="Mondongo0384" x="935" y="2940" width="935" height="980"/>
	<SubTexture name="Mondongo0385" x="935" y="2940" width="935" height="980"/>
	<SubTexture name="Mondongo0386" x="935" y="2940" width="935" height="980"/>
	<SubTexture name="Mondongo0387" x="935" y="2940" width="935" height="980"/>
	<SubTexture name="Mondongo0388" x="935" y="2940" width="935" height="980"/>
	<SubTexture name="Mondongo0389" x="935" y="2940" width="935" height="980"/>
	<SubTexture name="Mondongo0390" x="935" y="2940" width="935" height="980"/>
	<SubTexture name="Mondongo0391" x="935" y="2940" width="935" height="980"/>
	<SubTexture name="Mondongo0392" x="935" y="2940" width="935" height="980"/>
	<SubTexture name="Mondongo0393" x="935" y="2940" width="935" height="980"/>
	<SubTexture name="Mondongo0394" x="935" y="2940" width="935" height="980"/>
	<SubTexture name="Mondongo0395" x="935" y="2940" width="935" height="980"/>
	<SubTexture name="Mondongo0396" x="935" y="2940" width="935" height="980"/>
	<SubTexture name="Mondongo0397" x="935" y="2940" width="935" height="980"/>
	<SubTexture name="Mondongo0398" x="935" y="2940" width="935" height="980"/>
	<SubTexture name="Mondongo0399" x="935" y="2940" width="935" height="980"/>
	<SubTexture name="Mondongo0400" x="935" y="2940" width="935" height="980"/>
</TextureAtlas>
